[
  {
    "url": "http://weixin.sogou.com/weixin?type=2&query=%E4%B8%81%E9%A6%99%E5%A6%88%E5%A6%88+%E5%8D%83%E4%B8%87%E5%88%AB%E5%8E%BB%E4%BF%AE%E8%84%9A%E5%BA%97%E7%9E%8E%E6%8A%98%E8%85%BE%EF%BC%81%0A%E8%BF%99%E4%B8%AA%E6%96%B9%E6%B3%95%E6%9C%89%E6%95%88%E5%8F%88%E7%9C%81%E9%92%B1%0A%E5%BE%88%E5%A4%9A%E4%BA%BA%E5%8D%B4%E4%B8%8D%E6%95%A2%E7%94%A8%E2%80%A6%E2%80%A6%0A%0A%0A%E8%A6%81%E8%AF%B4%E6%9C%80%E5%9B%B0%E6%89%B0%E6%88%90%E5%B9%B4%E4%BA%BA%E7%9A%84%E6%8C%87%E7%94%B2%E9%97%AE%E9%A2%98%EF%BC%8C%E9%9D%9E%E3%80%8C%E7%81%B0%E6%8C%87%E7%94%B2%E3%80%8D%E8%8E%AB%E5%B1%9E%EF%BC%81%5B%E5%A4%B1%E6%9C%9B%5D%20%20%0A%0A%E8%99%BD%E8%AF%B4%E5%AE%83%E7%9A%84%E4%BC%A4%E5%AE%B3%E5%BA%A6%E4%B8%8D%E9%AB%98%EF%BC%8C%E4%BD%86%E5%8F%8D%E5%8F%8D%E5%A4%8D%E5%A4%8D%E5%BE%88%E6%8A%98%E7%A3%A8%E4%BA%BA%EF%BC%8C%E5%AE%83%E5%AF%BC%E8%87%B4%E6%8C%87%E7%94%B2%E5%8F%98%E8%89%B2%E3%80%81%E5%8F%98%E5%8E%9A%E3%80%81%E5%8F%98%E7%A2%8E%E6%88%96....",
    "date": "Tue, 24 Ma",
    "title": "千万别去修脚店瞎折腾！\n这个方法有效又省钱\n很多人却不敢用……\n\n\n要说最困扰成年人的指甲问题，非「灰指甲」莫属！[失望]  \n\n虽说它的伤害度不高，但反反复复很折磨人，它导致指甲变色、变厚、变碎或....",
    "summary": "千万别去修脚店瞎折腾！这个方法有效又省钱很多人却不敢用……要说最困扰成年人的指甲问题，非「灰指甲」莫属！[失望]  虽说它的伤害度不高，但反反复复很折磨人，它导致指甲变色、变厚、变碎或畸形，极大地影响日常社交。最烦人的是，灰指甲还会传染。不仅感染身体其他部位，导致足癣（脚气）、手癣等，引起发痒、脱皮、水疱。⚠️ 还会通过共用的指甲剪、拖鞋、毛巾，传染给家人，包括孩子👦🏻。所以有灰指甲后，一定要第一...",
    "author": "丁香妈妈",
    "tags": [
      "dxy_mom"
    ],
    "points": 9999
  },
  {
    "url": "http://weixin.sogou.com/weixin?type=2&query=%E4%B8%81%E9%A6%99%E5%A6%88%E5%A6%88+%E5%AE%9D%E5%AE%9D%E6%89%8B%E6%8C%87%E8%84%B1%E7%9A%AE%EF%BC%8C%E6%80%8E%E4%B9%88%E5%8A%9E%EF%BC%9F",
    "date": "Mon, 23 Ma",
    "title": "宝宝手指脱皮，怎么办？",
    "summary": "换季季节，宝宝容易出现手指脱皮的情况，家长们可以这样做：避免手部皮肤受刺激宝宝手指脱皮，最常见的原因是手部湿疹。护理湿疹宝宝，关键是保护皮肤免受刺激，远离过于干燥、过热过冷或温度变化较大的环境，防止宝宝因为瘙痒而反复抓挠皮肤。注意保湿可以多用流水冲洗来取代酒精和消毒剂消毒，洗手后立刻抹上护肤霜保湿。遵医嘱用药如果宝宝确诊为手部湿疹或者特应性皮炎，在医生指导下，可以适当使用弱效激素类软膏，如地奈德等...",
    "author": "丁香妈妈",
    "tags": [
      "dxy_mom"
    ],
    "points": 9999
  },
  {
    "url": "http://weixin.sogou.com/weixin?type=2&query=%E4%B8%81%E9%A6%99%E5%A6%88%E5%A6%88+6%20%E5%B2%81%E5%89%8D%E6%9C%80%E5%A5%BD%E4%B8%8D%E8%A6%81%E3%80%8C%E6%95%99%E3%80%8D%E5%AD%A9%E5%AD%90%E7%94%BB%E7%94%BB%EF%BC%81%E5%8E%9F%E5%9B%A0%E5%B1%85%E7%84%B6%E6%98%AF%E2%80%A6%E2%80%A6",
    "date": "Mon, 23 Ma",
    "title": "6 岁前最好不要「教」孩子画画！原因居然是……",
    "summary": "毕加索曾经说过：「我用了一生的时间，去学习像小孩子那样画画。」因为在艺术创作中，即便是艺术大师的想象力，也未必能高过小孩，可以说，每个孩子，在幼儿时期都是天生的艺术家。图片来源：图虫创意但是，家长「教」宝宝画画的一些方式，反而可能破坏宝宝的想象力：一是用成人思维干扰：在宝宝画画时，总是坐在旁边提指导意见「房子要画成方形的」、「太阳应该是橙色的」、「小河怎么画到天上啦」等等；二是让宝宝依葫芦画瓢：家...",
    "author": "丁香妈妈",
    "tags": [
      "dxy_mom"
    ],
    "points": 9999
  },
  {
    "url": "http://weixin.sogou.com/weixin?type=2&query=%E4%B8%81%E9%A6%99%E5%A6%88%E5%A6%88+%E5%AD%A9%E5%AD%90%E4%B8%80%E7%9B%B4%E5%92%B3%E5%97%BD%EF%BC%8C%E4%BC%9A%E5%92%B3%E5%87%BA%E8%82%BA%E7%82%8E%E5%90%97%EF%BC%9F",
    "date": "Mon, 23 Ma",
    "title": "孩子一直咳嗽，会咳出肺炎吗？",
    "summary": "孩子咳嗽反复不好，家长会担心是不是得了肺炎。其实这是一个错误观念，事实是「咳嗽本身不会引发肺炎，相反是肺炎引起了咳嗽」。咳嗽只是症状，它可以由很多原因导致，肺炎只是其中一个原因。如果孩子咳嗽很严重，影响到日常生活和睡眠，家长又拿捏不准原因时，建议咨询专业的医生，早治疗早安心。孩子咳嗽老不好立即咨询三甲医生👇*线上就诊应提供具有明确诊断的病例资料，如门诊病历、诊断证明等，以帮助医生更准确地判断病情。...",
    "author": "丁香妈妈",
    "tags": [
      "dxy_mom"
    ],
    "points": 9999
  },
  {
    "url": "http://weixin.sogou.com/weixin?type=2&query=%E4%B8%81%E9%A6%99%E5%A6%88%E5%A6%88+%E4%B8%BA%E4%BB%80%E4%B9%88%E5%AD%A9%E5%AD%90%E6%9B%B4%E7%88%B1%E5%AF%B9%E5%A6%88%E5%A6%88%E5%8F%91%E8%84%BE%E6%B0%94%EF%BC%9F%E7%9C%9F%E4%B8%8D%E6%98%AF%E6%83%AF%E7%9A%84",
    "date": "Mon, 23 Ma",
    "title": "为什么孩子更爱对妈妈发脾气？真不是惯的",
    "summary": "我们在生活中常常会发现一个令人无奈的现象：孩子，似乎总爱对妈妈发脾气……和其他人出门，娃乖巧懂事，全程可以自己走，累了也能坚持。但和妈妈出门，爱撒娇，总要抱，一不如意就撒泼打滚。在幼儿园里犯错，老师批评能欣然接受，立马改正。回到家后，妈妈只是简单问问在幼儿园发生了什么，就立马翻脸，炸毛，又哭又闹。图片来源：giphy面对这么巨大的反差，旁人会说：「是不是你平时太惯着孩子了，才会这样？别人说孩子， ...",
    "author": "丁香妈妈",
    "tags": [
      "dxy_mom"
    ],
    "points": 9999
  }
]